azure/ai/documentintelligence/__init__.py
azure/ai/documentintelligence/_client.py
azure/ai/documentintelligence/_configuration.py
azure/ai/documentintelligence/_model_base.py
azure/ai/documentintelligence/_patch.py
azure/ai/documentintelligence/_serialization.py
azure/ai/documentintelligence/_validation.py
azure/ai/documentintelligence/_vendor.py
azure/ai/documentintelligence/_version.py
azure/ai/documentintelligence/py.typed
azure/ai/documentintelligence/_operations/__init__.py
azure/ai/documentintelligence/_operations/_operations.py
azure/ai/documentintelligence/_operations/_patch.py
azure/ai/documentintelligence/aio/__init__.py
azure/ai/documentintelligence/aio/_client.py
azure/ai/documentintelligence/aio/_configuration.py
azure/ai/documentintelligence/aio/_patch.py
azure/ai/documentintelligence/aio/_vendor.py
azure/ai/documentintelligence/aio/_operations/__init__.py
azure/ai/documentintelligence/aio/_operations/_operations.py
azure/ai/documentintelligence/aio/_operations/_patch.py
azure/ai/documentintelligence/models/__init__.py
azure/ai/documentintelligence/models/_enums.py
azure/ai/documentintelligence/models/_models.py
azure/ai/documentintelligence/models/_patch.py
azure_ai_documentintelligence-1.0.1.dist-info/LICENSE
azure_ai_documentintelligence-1.0.1.dist-info/METADATA
azure_ai_documentintelligence-1.0.1.dist-info/WHEEL
azure_ai_documentintelligence-1.0.1.dist-info/top_level.txt
azure_ai_documentintelligence-1.0.1.dist-info/RECORD
